smfscraper/__init__.py
smfscraper-0.0.3.dist-info/LICENSE
smfscraper-0.0.3.dist-info/METADATA
smfscraper-0.0.3.dist-info/WHEEL
smfscraper-0.0.3.dist-info/top_level.txt
smfscraper-0.0.3.dist-info/RECORD
