Metadata-Version: 2.1
Name: smfscraper
Version: 0.0.3
Summary: Wrapper for scraping simplemachineforums
Home-page: https://github.com/ryuuzu/smfscaper
Author: Utsav Magar
Author-email: utsavmagar88728@gmail.com
License: UNKNOWN
Keywords: python,first package,smf,simplemachineforums,smfscraper,smfapi
Platform: UNKNOWN
Classifier: Development Status :: 3 - Alpha
Classifier: Intended Audience :: Education
Classifier: Programming Language :: Python :: 2
Classifier: Programming Language :: Python :: 3
Classifier: Operating System :: MacOS :: MacOS X
Classifier: Operating System :: Microsoft :: Windows
Requires-Python: >=3.6
Requires-Dist: requests
Requires-Dist: beautifulsoup4
